fastapi_auth_manager/__init__.py
fastapi_auth_manager/auth.py
fastapi_auth_manager/models.py
fastapi_auth_manager/utils.py
fastapi_auth_manager-0.1.0.dist-info/METADATA
fastapi_auth_manager-0.1.0.dist-info/WHEEL
fastapi_auth_manager-0.1.0.dist-info/top_level.txt
fastapi_auth_manager-0.1.0.dist-info/RECORD
