Metadata-Version: 2.1
Name: fastapi_auth_manager
Version: 0.1.0
Summary: A simple authentication management library for FastAPI
Author: Mirzonabot Mirzonabotov
Author-email: mirzonabot.mirzonabotov99@gmail.com
Classifier: Programming Language :: Python :: 3
Classifier: License :: OSI Approved :: MIT License
Classifier: Operating System :: OS Independent
Requires-Python: >=3.6
Requires-Dist: fastapi
Requires-Dist: python-jose
Requires-Dist: passlib[bcrypt]
Requires-Dist: pydantic
